pypokeapi/__init__.py
pypokeapi/pokeapi.py
pypokeapi-1.0.0.dist-info/LICENSE.txt
pypokeapi-1.0.0.dist-info/METADATA
pypokeapi-1.0.0.dist-info/WHEEL
pypokeapi-1.0.0.dist-info/top_level.txt
pypokeapi-1.0.0.dist-info/RECORD
