Metadata-Version: 2.1
Name: pypokeapi
Version: 1.0.0
Summary: A simple python wrapper for PokeAPI with many built in functions.
Author: Mattz
Project-URL: Homepage, https://github.com/m-attz/py-pokeapi
Project-URL: Issues, https://github.com/m-attz/py-pokeapi/issues
Classifier: Programming Language :: Python :: 3
Classifier: License :: OSI Approved :: GNU General Public License v3 or later (GPLv3+)
Classifier: Operating System :: OS Independent
Requires-Python: >=3.10
License-File: LICENSE.txt
